tests
fieldmaker
