Metadata-Version: 1.0
Name: django-fieldmaker
Version: 0.0.3
Summary: Dynamic form management in django
Home-page: http://github.com/cuker/
Author: Jason Kraus
Author-email: zbyte64@gmail.com
License: New BSD License
Keywords: django
Platform: UNKNOWN
Classifier: Programming Language :: Python
Classifier: Operating System :: OS Independent
Classifier: Natural Language :: English
Classifier: Development Status :: 3 - Alpha
Classifier: Intended Audience :: Developers
Classifier: Topic :: Internet :: WWW/HTTP :: Dynamic Content
